Metadata-Version: 2.1
Name: odoo8-addon-account-invoice-pricelist
Version: 8.0.1.1.0.99.dev17
Summary: Add partner pricelist on invoices
Home-page: http://www.grap.coop
Author: GRAP,Therp BV,Odoo Community Association (OCA)
Author-email: support@odoo-community.org
License: AGPL-3
Platform: UNKNOWN
Classifier: Programming Language :: Python
Classifier: Framework :: Odoo
Classifier: License :: OSI Approved :: GNU Affero General Public License v3
Requires-Python: ~=2.7
Requires-Dist: odoo8-addon-base-view-inheritance-extension
Requires-Dist: odoo (<9.0a,>=8.0a)
